dtocean/__init__.py
dtocean-2025.12.0.dev0.dist-info/METADATA
dtocean-2025.12.0.dev0.dist-info/WHEEL
dtocean-2025.12.0.dev0.dist-info/RECORD
