Metadata-Version: 2.4
Name: dtocean
Version: 2025.12.0.dev0
Summary: Design and techno-economic assessment of marine renewable energy arrays.
License-Expression: GPL-3.0-or-later
Author: The DTOcean Developers
Maintainer: Mathew Topper
Maintainer-email: damm_horse@yahoo.co.uk
Requires-Python: >=3.12,<3.13
Classifier: Programming Language :: Python :: 3
Classifier: Programming Language :: Python :: 3.12
